Workbook

Sheet Assumptions
A1: Assumptions
A3: Revenue drivers
A4: Opening customers | B4: 6300
A5: Monthly new customer rate | B5: 0.0578
A6: Monthly churn rate | B6: 0.0234
A7: Opening ARPU | B7: 118.95
A8: Monthly ARPU uplift | B8: 0.0097
A10: Cost drivers
A11: COGS as share of revenue | B11: 0.1833
A12: Opening headcount | B12: 18
A13: New hires per month | B13: 2
A14: Average salary | B14: 72000
A15: Payroll tax rate | B15: 0.1535
A16: Marketing as share of revenue | B16: 0.1273
A17: Monthly overhead | B17: 42500
A18: Monthly overhead inflation | B18: 0.0032
A20: Valuation drivers
A21: EBITDA multiple | B21: 13.6
A22: Net debt | B22: 3550000

Sheet Revenue
A1: Revenue build
A3: Month | C3: 1 | D3: =C3+1 -> 2 | E3: =D3+1 -> 3 | F3: =E3+1 -> 4 | G3: =F3+1 -> 5 | H3: =G3+1 -> 6 | I3: =H3+1 -> 7 | J3: =I3+1 -> 8 | K3: =J3+1 -> 9 | ... Z3: =Y3+1 -> 24
A5: Opening customers | C5: =Assumptions!$B$4 -> 6300 | D5: =C9 -> 6517 | E5: =D9 -> 6742 | F5: =E9 -> 6974 | G5: =F9 -> 7214 | H5: =G9 -> 7462 | I5: =H9 -> 7718 | J5: =I9 -> 7983 | K5: =J9 -> 8257 | ... Z5: =Y9 -> 13713
A6: New customers | C6: =ROUND(C5*Assumptions!$B$5,0) -> 364 | D6: =ROUND(D5*Assumptions!$B$5,0) -> 377 | E6: =ROUND(E5*Assumptions!$B$5,0) -> 390 | F6: =ROUND(F5*Assumptions!$B$5,0) -> 403 | G6: =ROUND(G5*Assumptions!$B$5,0) -> 417 | H6: =ROUND(H5*Assumptions!$B$5,0) -> 431 | I6: =ROUND(I5*Assumptions!$B$5,0) -> 446 | J6: =ROUND(J5*Assumptions!$B$5,0) -> 461 | ... Z6: =ROUND(Z5*Assumptions!$B$5,0) -> 793
A7: Churned customers | C7: =-ROUND(C5*Assumptions!$B$6,0) -> -147 | D7: =-ROUND(D5*Assumptions!$B$6,0) -> -152 | E7: =-ROUND(E5*Assumptions!$B$6,0) -> -158 | F7: =-ROUND(F5*Assumptions!$B$6,0) -> -163 | G7: =-ROUND(G5*Assumptions!$B$6,0) -> -169 | H7: =-ROUND(H5*Assumptions!$B$6,0) -> -175 | I7: =-ROUND(I5*Assumptions!$B$6,0) -> -181 | J7: =-ROUND(J5*Assumptions!$B$6,0) -> -187 | ... Z7: =-ROUND(Z5*Assumptions!$B$6,0) -> -321
A9: Closing customers | C9: =C5+C6+C7 -> 6517 | D9: =D5+D6+D7 -> 6742 | E9: =E5+E6+E7 -> 6974 | F9: =F5+F6+F7 -> 7214 | G9: =G5+G6+G7 -> 7462 | H9: =H5+H6+H7 -> 7718 | I9: =I5+I6+I7 -> 7983 | J9: =J5+J6+J7 -> 8257 | ... Z9: =Z5+Z6+Z7 -> 14185
A11: ARPU | C11: =Assumptions!$B$7 -> 118.95 | D11: =ROUND(C11*(1+Assumptions!$B$8),2) -> 120.1 | E11: =ROUND(D11*(1+Assumptions!$B$8),2) -> 121.26 | F11: =ROUND(E11*(1+Assumptions!$B$8),2) -> 122.44 | G11: =ROUND(F11*(1+Assumptions!$B$8),2) -> 123.63 | H11: =ROUND(G11*(1+Assumptions!$B$8),2) -> 124.83 | I11: =ROUND(H11*(1+Assumptions!$B$8),2) -> 126.04 | J11: =ROUND(I11*(1+Assumptions!$B$8),2) -> 127.26 | K11: =ROUND(J11*(1+Assumptions!$B$8),2) -> 128.49 | ... Z11: =ROUND(Y11*(1+Assumptions!$B$8),2) -> 148.52
A13: Average customers | C13: =ROUND((C5+C9)/2,0) -> 6409 | D13: =ROUND((D5+D9)/2,0) -> 6630 | E13: =ROUND((E5+E9)/2,0) -> 6858 | F13: =ROUND((F5+F9)/2,0) -> 7094 | G13: =ROUND((G5+G9)/2,0) -> 7338 | H13: =ROUND((H5+H9)/2,0) -> 7590 | I13: =ROUND((I5+I9)/2,0) -> 7851 | J13: =ROUND((J5+J9)/2,0) -> 8120 | ... Z13: =ROUND((Z5+Z9)/2,0) -> 13949
A15: Revenue | C15: =ROUND(C13*C11,0) -> 762351 | D15: =ROUND(D13*D11,0) -> 796263 | E15: =ROUND(E13*E11,0) -> 831601 | F15: =ROUND(F13*F11,0) -> 868589 | G15: =ROUND(G13*G11,0) -> 907197 | H15: =ROUND(H13*H11,0) -> 947460 | I15: =ROUND(I13*I11,0) -> 989540 | J15: =ROUND(J13*J11,0) -> 1033351 | ... Z15: =ROUND(Z13*Z11,0) -> 2071705
A17: Cumulative revenue | C17: =C15 -> 762351 | D17: =C17+D15 -> 1558614 | E17: =D17+E15 -> 2390215 | F17: =E17+F15 -> 3258804 | G17: =F17+G15 -> 4166001 | H17: =G17+H15 -> 5113461 | I17: =H17+I15 -> 6103001 | J17: =I17+J15 -> 7136352 | K17: =J17+K15 -> 8215540 | ... Z17: =Y17+Z15 -> 31543953

Sheet Costs
A1: Cost build
A3: Month | C3: =Revenue!C3 -> 1 | D3: =Revenue!D3 -> 2 | E3: =Revenue!E3 -> 3 | F3: =Revenue!F3 -> 4 | G3: =Revenue!G3 -> 5 | H3: =Revenue!H3 -> 6 | I3: =Revenue!I3 -> 7 | J3: =Revenue!J3 -> 8 | ... Z3: =Revenue!Z3 -> 24
A5: Headcount | C5: =Assumptions!$B$12 -> 18 | D5: =C5+Assumptions!$B$13 -> 20 | E5: =D5+Assumptions!$B$13 -> 22 | F5: =E5+Assumptions!$B$13 -> 24 | G5: =F5+Assumptions!$B$13 -> 26 | H5: =G5+Assumptions!$B$13 -> 28 | I5: =H5+Assumptions!$B$13 -> 30 | J5: =I5+Assumptions!$B$13 -> 32 | K5: =J5+Assumptions!$B$13 -> 34 | ... Z5: =Y5+Assumptions!$B$13 -> 64
A6: Salary cost | C6: =ROUND(C5*Assumptions!$B$14/12,0) -> 108000 | D6: =ROUND(D5*Assumptions!$B$14/12,0) -> 120000 | E6: =ROUND(E5*Assumptions!$B$14/12,0) -> 132000 | F6: =ROUND(F5*Assumptions!$B$14/12,0) -> 144000 | G6: =ROUND(G5*Assumptions!$B$14/12,0) -> 156000 | H6: =ROUND(H5*Assumptions!$B$14/12,0) -> 168000 | I6: =ROUND(I5*Assumptions!$B$14/12,0) -> 180000 | J6: =ROUND(J5*Assumptions!$B$14/12,0) -> 192000 | ... Z6: =ROUND(Z5*Assumptions!$B$14/12,0) -> 384000
A7: Payroll tax | C7: =ROUND(C6*Assumptions!$B$15,0) -> 16578 | D7: =ROUND(D6*Assumptions!$B$15,0) -> 18420 | E7: =ROUND(E6*Assumptions!$B$15,0) -> 20262 | F7: =ROUND(F6*Assumptions!$B$15,0) -> 22104 | G7: =ROUND(G6*Assumptions!$B$15,0) -> 23946 | H7: =ROUND(H6*Assumptions!$B$15,0) -> 25788 | I7: =ROUND(I6*Assumptions!$B$15,0) -> 27630 | J7: =ROUND(J6*Assumptions!$B$15,0) -> 29472 | ... Z7: =ROUND(Z6*Assumptions!$B$15,0) -> 58944
A8: Total staff cost | C8: =C6+C7 -> 124578 | D8: =D6+D7 -> 138420 | E8: =E6+E7 -> 152262 | F8: =F6+F7 -> 166104 | G8: =G6+G7 -> 179946 | H8: =H6+H7 -> 193788 | I8: =I6+I7 -> 207630 | J8: =J6+J7 -> 221472 | ... Z8: =Z6+Z7 -> 442944
A10: Cost of sales | C10: =ROUND(Revenue!C15*Assumptions!$B$11,0) -> 139739 | D10: =ROUND(Revenue!D15*Assumptions!$B$11,0) -> 145955 | E10: =ROUND(Revenue!E15*Assumptions!$B$11,0) -> 152432 | F10: =ROUND(Revenue!F15*Assumptions!$B$11,0) -> 159212 | G10: =ROUND(Revenue!G15*Assumptions!$B$11,0) -> 166289 | H10: =ROUND(Revenue!H15*Assumptions!$B$11,0) -> 173669 | I10: =ROUND(Revenue!I15*Assumptions!$B$11,0) -> 181383 | J10: =ROUND(Revenue!J15*Assumptions!$B$11,0) -> 189413 | ... Z10: =ROUND(Revenue!Z15*Assumptions!$B$11,0) -> 379744
A11: Marketing | C11: =ROUND(Revenue!C15*Assumptions!$B$16,0) -> 97047 | D11: =ROUND(Revenue!D15*Assumptions!$B$16,0) -> 101364 | E11: =ROUND(Revenue!E15*Assumptions!$B$16,0) -> 105863 | F11: =ROUND(Revenue!F15*Assumptions!$B$16,0) -> 110571 | G11: =ROUND(Revenue!G15*Assumptions!$B$16,0) -> 115486 | H11: =ROUND(Revenue!H15*Assumptions!$B$16,0) -> 120612 | I11: =ROUND(Revenue!I15*Assumptions!$B$16,0) -> 125968 | J11: =ROUND(Revenue!J15*Assumptions!$B$16,0) -> 131546 | ... Z11: =ROUND(Revenue!Z15*Assumptions!$B$16,0) -> 263728
A12: Overhead | C12: =ROUND(Assumptions!$B$17,0) -> 42500 | D12: =ROUND(C12*(1+Assumptions!$B$18),0) -> 42636 | E12: =ROUND(D12*(1+Assumptions!$B$18),0) -> 42772 | F12: =ROUND(E12*(1+Assumptions!$B$18),0) -> 42909 | G12: =ROUND(F12*(1+Assumptions!$B$18),0) -> 43046 | H12: =ROUND(G12*(1+Assumptions!$B$18),0) -> 43184 | I12: =ROUND(H12*(1+Assumptions!$B$18),0) -> 43322 | J12: =ROUND(I12*(1+Assumptions!$B$18),0) -> 43461 | K12: =ROUND(J12*(1+Assumptions!$B$18),0) -> 43600 | ... Z12: =ROUND(Y12*(1+Assumptions!$B$18),0) -> 45741
A14: Total costs | C14: =C8+C10+C11+C12 -> 403864 | D14: =D8+D10+D11+D12 -> 428375 | E14: =E8+E10+E11+E12 -> 453329 | F14: =F8+F10+F11+F12 -> 478796 | G14: =G8+G10+G11+G12 -> 504767 | H14: =H8+H10+H11+H12 -> 531253 | I14: =I8+I10+I11+I12 -> 558303 | J14: =J8+J10+J11+J12 -> 585892 | ... Z14: =Z8+Z10+Z11+Z12 -> 1132157

Sheet P&L
A1: Profit and loss
A3: Month | C3: =Revenue!C3 -> 1 | D3: =Revenue!D3 -> 2 | E3: =Revenue!E3 -> 3 | F3: =Revenue!F3 -> 4 | G3: =Revenue!G3 -> 5 | H3: =Revenue!H3 -> 6 | I3: =Revenue!I3 -> 7 | J3: =Revenue!J3 -> 8 | ... Z3: =Revenue!Z3 -> 24 | AA3: Total
A5: Revenue | C5: =Revenue!C15 -> 762351 | D5: =Revenue!D15 -> 796263 | E5: =Revenue!E15 -> 831601 | F5: =Revenue!F15 -> 868589 | G5: =Revenue!G15 -> 907197 | H5: =Revenue!H15 -> 947460 | I5: =Revenue!I15 -> 989540 | J5: =Revenue!J15 -> 1033351 | ... Z5: =Revenue!Z15 -> 2071705 | AA5: =SUM(C5:Z5) -> 31543953
A6: Cost of sales | C6: =-Costs!C10 -> -139739 | D6: =-Costs!D10 -> -145955 | E6: =-Costs!E10 -> -152432 | F6: =-Costs!F10 -> -159212 | G6: =-Costs!G10 -> -166289 | H6: =-Costs!H10 -> -173669 | I6: =-Costs!I10 -> -181383 | J6: =-Costs!J10 -> -189413 | ... Z6: =-Costs!Z10 -> -379744 | AA6: =SUM(C6:Z6) -> -5782006
A7: Gross profit | C7: =C5+C6 -> 622612 | D7: =D5+D6 -> 650308 | E7: =E5+E6 -> 679169 | F7: =F5+F6 -> 709377 | G7: =G5+G6 -> 740908 | H7: =H5+H6 -> 773791 | I7: =I5+I6 -> 808157 | J7: =J5+J6 -> 843938 | ... Z7: =Z5+Z6 -> 1691961 | AA7: =SUM(C7:Z7) -> 25761947
A8: Gross margin | C8: =IF(C5=0,0,ROUND(C7/C5,4)) -> 0.8167 | D8: =IF(D5=0,0,ROUND(D7/D5,4)) -> 0.8167 | E8: =IF(E5=0,0,ROUND(E7/E5,4)) -> 0.8167 | F8: =IF(F5=0,0,ROUND(F7/F5,4)) -> 0.8167 | G8: =IF(G5=0,0,ROUND(G7/G5,4)) -> 0.8167 | H8: =IF(H5=0,0,ROUND(H7/H5,4)) -> 0.8167 | I8: =IF(I5=0,0,ROUND(I7/I5,4)) -> 0.8167 | J8: =IF(J5=0,0,ROUND(J7/J5,4)) -> 0.8167 | ... Z8: =IF(Z5=0,0,ROUND(Z7/Z5,4)) -> 0.8167
A10: Staff costs | C10: =-Costs!C8 -> -124578 | D10: =-Costs!D8 -> -138420 | E10: =-Costs!E8 -> -152262 | F10: =-Costs!F8 -> -166104 | G10: =-Costs!G8 -> -179946 | H10: =-Costs!H8 -> -193788 | I10: =-Costs!I8 -> -207630 | J10: =-Costs!J8 -> -221472 | ... Z10: =-Costs!Z8 -> -442944 | AA10: =SUM(C10:Z10) -> -6810264
A11: Marketing | C11: =-Costs!C11 -> -97047 | D11: =-Costs!D11 -> -101364 | E11: =-Costs!E11 -> -105863 | F11: =-Costs!F11 -> -110571 | G11: =-Costs!G11 -> -115486 | H11: =-Costs!H11 -> -120612 | I11: =-Costs!I11 -> -125968 | J11: =-Costs!J11 -> -131546 | ... Z11: =-Costs!Z11 -> -263728 | AA11: =SUM(C11:Z11) -> -4015547
A12: Overhead | C12: =-Costs!C12 -> -42500 | D12: =-Costs!D12 -> -42636 | E12: =-Costs!E12 -> -42772 | F12: =-Costs!F12 -> -42909 | G12: =-Costs!G12 -> -43046 | H12: =-Costs!H12 -> -43184 | I12: =-Costs!I12 -> -43322 | J12: =-Costs!J12 -> -43461 | ... Z12: =-Costs!Z12 -> -45741 | AA12: =SUM(C12:Z12) -> -1058431
A13: Total operating costs | C13: =C10+C11+C12 -> -264125 | D13: =D10+D11+D12 -> -282420 | E13: =E10+E11+E12 -> -300897 | F13: =F10+F11+F12 -> -319584 | G13: =G10+G11+G12 -> -338478 | H13: =H10+H11+H12 -> -357584 | I13: =I10+I11+I12 -> -376920 | J13: =J10+J11+J12 -> -396479 | ... Z13: =Z10+Z11+Z12 -> -752413 | AA13: =SUM(C13:Z13) -> -11884242
A15: EBITDA | C15: =C7+C13 -> 358487 | D15: =D7+D13 -> 367888 | E15: =E7+E13 -> 378272 | F15: =F7+F13 -> 389793 | G15: =G7+G13 -> 402430 | H15: =H7+H13 -> 416207 | I15: =I7+I13 -> 431237 | J15: =J7+J13 -> 447459 | ... Z15: =Z7+Z13 -> 939548 | AA15: =SUM(C15:Z15) -> 13877705
A16: EBITDA margin | C16: =IF(C5=0,0,ROUND(C15/C5,4)) -> 0.4702 | D16: =IF(D5=0,0,ROUND(D15/D5,4)) -> 0.462 | E16: =IF(E5=0,0,ROUND(E15/E5,4)) -> 0.4549 | F16: =IF(F5=0,0,ROUND(F15/F5,4)) -> 0.4488 | G16: =IF(G5=0,0,ROUND(G15/G5,4)) -> 0.4436 | H16: =IF(H5=0,0,ROUND(H15/H5,4)) -> 0.4393 | I16: =IF(I5=0,0,ROUND(I15/I5,4)) -> 0.4358 | J16: =IF(J5=0,0,ROUND(J15/J5,4)) -> 0.433 | ... Z16: =IF(Z5=0,0,ROUND(Z15/Z5,4)) -> 0.4535
A18: Cumulative EBITDA | C18: =C15 -> 358487 | D18: =C18+D15 -> 726375 | E18: =D18+E15 -> 1104647 | F18: =E18+F15 -> 1494440 | G18: =F18+G15 -> 1896870 | H18: =G18+H15 -> 2313077 | I18: =H18+I15 -> 2744314 | J18: =I18+J15 -> 3191773 | K18: =J18+K15 -> 3656851 | ... Z18: =Y18+Z15 -> 13877705

Sheet Valuation
A1: Valuation
A3: Total revenue | B3: =Revenue!Z17 -> 31543953
A4: Total EBITDA | B4: ='P&L'!AA15 -> 13877705
A5: Exit run rate EBITDA | B5: =SUM('P&L'!O15:Z15) -> 8705107
A6: EBITDA multiple | B6: =Assumptions!$B$21 -> 13.6
A7: Enterprise value | B7: =ROUND(B5*B6,0) -> 118389455
A8: Net debt | B8: =Assumptions!$B$22 -> 3550000
A9: Equity value | B9: =B7-B8 -> 114839455
A11: Average monthly EBITDA | B11: =AVERAGE('P&L'!C15:Z15) -> 578237.71
A12: Best month | B12: =MAX('P&L'!C15:Z15) -> 939548
A13: Worst month | B13: =MIN('P&L'!C15:Z15) -> 358487
A14: Sum of positive months | B14: =SUMIF('P&L'!C15:Z15,">0") -> 13877705
A15: Best to worst swing | B15: =ABS(B12-B13) -> 581061
